setup.py
twswebrpc/__init__.py
twswebrpc/client.py
twswebrpc/encoder.py
twswebrpc/resource.py
twswebrpc.egg-info/PKG-INFO
twswebrpc.egg-info/SOURCES.txt
twswebrpc.egg-info/dependency_links.txt
twswebrpc.egg-info/requires.txt
twswebrpc.egg-info/top_level.txt
twswebrpc.egg-info/zip-safe