Metadata-Version: 1.1
Name: twswebrpc
Version: 0.1.1
Summary: Twisted JSON RPC web Client and web Resource
Home-page: https://github.com/ldjebran/twswebrpc
Author: Djebran Lezzoum
Author-email: ldjebran@gmail.com
License: Apache
Keywords: twisted rpc web json
Platform: any
Classifier: Programming Language :: Python :: 2.7
